MalwareProxyX/__init__.py
MalwareProxyX/__main__.py
MalwareProxyX/binary.py
MalwareProxyX/core.py
MalwareProxyX/networking.py
MalwareProxyX/version.py
malwareproxyx-0.1.1.dist-info/LICENSE.txt
malwareproxyx-0.1.1.dist-info/METADATA
malwareproxyx-0.1.1.dist-info/WHEEL
malwareproxyx-0.1.1.dist-info/entry_points.txt
malwareproxyx-0.1.1.dist-info/top_level.txt
malwareproxyx-0.1.1.dist-info/RECORD
