Metadata-Version: 2.1
Name: malwareproxyx
Version: 0.1.1
Summary: Real Time Malware Payload Injection In User Binary Downloads Utilising MITM Proxy
Home-page: https://github.com/darshkpatel/MalwareProxyX
Author: Darsh Patel
Author-email: darshkpatel@gmail.com
License: UNKNOWN
Project-URL: Bug Reports, https://github.com/darshkpatel/MalwareProxyX/issues
Project-URL: Say Thanks!, https://darshkpatel.com/
Project-URL: Source, https://github.com/darshkpatel/MalwareProxyX/
Keywords: mitmproxy,malware,security
Platform: UNKNOWN
Classifier: Development Status :: 3 - Alpha
Classifier: Intended Audience :: Developers
Classifier: Topic :: Security
Classifier: License :: OSI Approved :: BSD License
Classifier: Programming Language :: Python :: 3
Classifier: Programming Language :: Python :: 3.6
Classifier: Programming Language :: Python :: 3.7
Classifier: Programming Language :: Python :: 3.8
Classifier: Programming Language :: Python :: 3.9
Classifier: Programming Language :: Python :: 3 :: Only
Requires-Python: >=3.6, <4
Requires-Dist: mitmproxy (>=5.3.0)
Requires-Dist: pefile (>=2019.4.18)
Provides-Extra: test
Requires-Dist: check-manifest ; extra == 'test'
Requires-Dist: coverage ; extra == 'test'
Requires-Dist: flake8 ; extra == 'test'
Requires-Dist: pytest ; extra == 'test'
